lmflow/__init__.py
lmflow/args.py
lmflow/version.py
lmflow/datasets/__init__.py
lmflow/datasets/dataset.py
lmflow/models/__init__.py
lmflow/models/auto_model.py
lmflow/models/base_model.py
lmflow/models/decoder_model.py
lmflow/models/encoder_decoder_model.py
lmflow/models/hf_decoder_model.py
lmflow/models/hf_encoder_decoder_model.py
lmflow/models/regression_model.py
lmflow/models/text_regression_model.py
lmflow/models/interfaces/__init__.py
lmflow/models/interfaces/tunable.py
lmflow/pipeline/__init__.py
lmflow/pipeline/auto_pipeline.py
lmflow/pipeline/base_aligner.py
lmflow/pipeline/base_pipeline.py
lmflow/pipeline/base_tuner.py
lmflow/pipeline/finetuner.py
lmflow/pipeline/inferencer.py
lmflow/pipeline/raft_aligner.py
lmflow/pipeline/utils/__init__.py
lmflow/pipeline/utils/raft_trainer.py
lmflow/utils/__init__.py
lmflow/utils/constants.py
lmflow/utils/flash_attention/__init__.py
lmflow/utils/flash_attention/gpt_neo_flash_attention.py
lmflow/utils/flash_attention/llama_flash_attention.py
lmflow_pretrainer-0.0.1.dist-info/LICENSE
lmflow_pretrainer-0.0.1.dist-info/METADATA
lmflow_pretrainer-0.0.1.dist-info/WHEEL
lmflow_pretrainer-0.0.1.dist-info/top_level.txt
lmflow_pretrainer-0.0.1.dist-info/RECORD
